statsfiles/__init__.py
statsfiles/__main__.py
statsfiles/copy_essential.py
statsfiles/statsarrays.py
statsfiles/statsfiles.py
statsfiles/statsobs.py
statsfiles/statsparams.py
statsfiles/data/cdh_params.yml
statsfiles/data/patrick_params.yml
statsfiles/tests/__init__.py
statsfiles/tests/test_statsarrays.py
statsfiles/tests/test_statsobs.py
statsfiles/tests/test_statsparams.py
statsfiles-2.3.0.dist-info/LICENSE
statsfiles-2.3.0.dist-info/METADATA
statsfiles-2.3.0.dist-info/WHEEL
statsfiles-2.3.0.dist-info/top_level.txt
statsfiles-2.3.0.dist-info/RECORD
