Metadata-Version: 2.1
Name: statsfiles
Version: 2.3.0
Summary: statsfiles for stats on files.
Home-page: https://github.com/ZGCDDoo/statsfiles
Author: Charles-David Hevert
Author-email: charles-david.hebert@usherbrooke.ca
License: MIT
Keywords: Statistics
Platform: UNKNOWN
Classifier: Development Status :: 4 - Beta
Classifier: Intended Audience :: Developers
Classifier: Topic :: Software Development :: Build Tools
Classifier: License :: OSI Approved :: MIT License
Classifier: Programming Language :: Python :: 3.6
Requires-Dist: numpy
Requires-Dist: scipy
Requires-Dist: pyyaml
